cwl_loader/__about__.py
cwl_loader/__init__.py
cwl_loader/sort.py
cwl_loader/utils.py
cwl_loader-0.15.0.dist-info/METADATA
cwl_loader-0.15.0.dist-info/WHEEL
cwl_loader-0.15.0.dist-info/licenses/LICENSE
cwl_loader-0.15.0.dist-info/licenses/NOTICE
cwl_loader-0.15.0.dist-info/RECORD
