Metadata-Version: 2.4
Name: cwl-loader
Version: 0.15.0
Summary: Utility to load a CWL (remote) document
Project-URL: Documentation, https://github.com/eoap/cwl-loader#readme
Project-URL: Issues, https://github.com/eoap/cwl-loader/issues
Project-URL: Source, https://github.com/eoap/cwl-loader
Author-email: Fabrice Brito <info@terradue.com>, Simone Tripodi <info@terradue.com>
License-Expression: MIT
License-File: LICENSE
License-File: NOTICE
Classifier: Development Status :: 4 - Beta
Classifier: Programming Language :: Python
Classifier: Programming Language :: Python :: 3.8
Classifier: Programming Language :: Python :: 3.9
Classifier: Programming Language :: Python :: 3.10
Classifier: Programming Language :: Python :: 3.11
Classifier: Programming Language :: Python :: 3.12
Classifier: Programming Language :: Python :: Implementation :: CPython
Classifier: Programming Language :: Python :: Implementation :: PyPy
Requires-Python: >=3.8
Requires-Dist: cwl-utils>=0.40
Requires-Dist: cwltool>=3.1.20250110105449
Requires-Dist: loguru
Requires-Dist: ruamel-yaml>=0.18.15
